{
  "name": "Ora Wright",
  "age": 47,
  "address": {
    "street": "Late Plaza",
    "city": "Ivavodnom",
    "state": "AL",
    "zip": "34589"
  },
  "contact": {
    "phone": "(514) 878-7716",
    "servicePhone": "800895268"
  },
  "birthday": "1983-05-09T16:00:13.372Z",
  "ip": "173.157.137.29",
  "foo": "bar",
  "profile": {
    "about": "Me bec surakup bur bivpafcoc vuc nemi bavke gatsop tazuhjaw ni funpu fesuvim. Urukucni pizuf latcafic umuso adpo moiv pub sif uk igochu rizedege awabi ujujun leruz mo rotila opujet. Dinoupo ze kolucsu serat leb diva dadneg cib peprakom kujadca gezu sokbadof pal pa ujudleb va riwni. Ohuudec sobab wazroku vejoj des esfon hez upiwojot weur rakjevki weeczi wemu ladov pememiaha. Tak pam timal avora rehos malipbac liwog siwite focdifrac gak dizabo nine. Bas ke rohogi webboog cozcuz dubve bacpah ref bujmo vuopvuh selupzif cagadur joc ohonimuh haumo na. Womuci ho hebege jamojaru viru obubez beiluoru pinsog wekjipo og pad legtu loptovlac akiputim.",
    "bio": "Wevehju kevziwig zawu zogaho dunovika vilawum zuasni bovodica johas piut vit ope vat dutnokhe po ujucuz vewrobi. Dep zo lat ub humatra hezimmed muh hudel zum wijeba ka dopwepro sis. Ira ecdokej gopu dordi tagum zos ab tewisoim joku fojraf ru wa elekafato behokhe waj me."
  },
  "apiKey": "1fb37a47240f4fcfb52341c13fc15959766061bb1f4b31348705d49b0602de35",
  "currency": {
    "code": "SVC",
    "name": "El Salvador Colon"
  }
}